<?xml version="1.0" ?>
<tv generator-info-name="TVTV.us EPG Converter" generator-info-url="https://www.tvtv.us">
  <channel id="55596">
    <display-name lang="en">MLB 1</display-name>
  </channel>
  <channel id="66112">
    <display-name lang="en">MLB 2</display-name>
  </channel>
  <channel id="72810">
    <display-name lang="en">MLB 3</display-name>
  </channel>
  <channel id="72824">
    <display-name lang="en">MLB 4</display-name>
  </channel>
  <channel id="72825">
    <display-name lang="en">MLB 5</display-name>
  </channel>
  <channel id="72826">
    <display-name lang="en">MLB 6</display-name>
  </channel>
  <channel id="72827">
    <display-name lang="en">MLB 7</display-name>
  </channel>
  <channel id="72828">
    <display-name lang="en">MLB 8</display-name>
  </channel>
  <programme start="20250923023000Z" stop="20250923090000Z" channel="55596">
    <title lang="en">MLB Extra Innings</title>
    <category lang="en">Sports Filler</category>
    <desc lang="en">Type: O. runTime: 390 min. Duration: 240 min (differs from runTime). Flags: HD 720p, HDTV.</desc>
  </programme>
  <programme start="20250923090000Z" stop="20250923100000Z" channel="55596">
    <title lang="en">MLB Extra Innings</title>
    <category lang="en">Sports Filler</category>
    <desc lang="en">Type: O. runTime: 60 min. Flags: HD 720p, HDTV.</desc>
  </programme>
  <programme start="20250923100000Z" stop="20250923180000Z" channel="55596">
    <title lang="en">MLB Extra Innings</title>
    <category lang="en">Sports Filler</category>
    <desc lang="en">Type: O. runTime: 480 min. Flags: HD 720p, HDTV.</desc>
  </programme>
  <programme start="20250923180000Z" stop="20250923220000Z" channel="55596">
    <title lang="en">MLB Extra Innings</title>
    <category lang="en">Sports Filler</category>
    <desc lang="en">Type: O. runTime: 240 min. Flags: HD 720p, HDTV.</desc>
  </programme>
  <programme start="20250923220000Z" stop="20250923223000Z" channel="55596">
    <title lang="en">MLB Pregame</title>
    <category lang="en">Sports Filler</category>
    <desc lang="en">Type: O. runTime: 30 min. Flags: Live, CC, HD 720p, HDTV, Subject to blackout. Subject to blackout.</desc>
    <premiere/>
    <subtitles type="teletext"/>
  </programme>
  <programme start="20250923223000Z" stop="20250924013000Z" channel="55596">
    <title lang="en">MLB Baseball</title>
    <sub-title lang="en">Tampa Bay Rays at Baltimore Orioles</sub-title>
    <category lang="en">Sports</category>
    <desc lang="en">Type: S. runTime: 180 min. Flags: Live, CC, HD 720p, HDTV, Subject to blackout. Subject to blackout.</desc>
    <premiere/>
    <subtitles type="teletext"/>
  </programme>
  <programme start="20250924013000Z" stop="20250924043000Z" channel="55596">
    <title lang="en">MLB Baseball</title>
    <sub-title lang="en">St. Louis Cardinals at San Francisco Giants</sub-title>
    <category lang="en">Sports</category>
    <desc lang="en">Type: S. runTime: 180 min. Flags: Live, CC, HD 720p, HDTV, Subject to blackout. Subject to blackout.</desc>
    <premiere/>
    <subtitles type="teletext"/>
  </programme>
  <programme start="20250924043000Z" stop="20250924050000Z" channel="55596">
    <title lang="en">MLB Postgame</title>
    <category lang="en">Sports Filler</category>
    <desc lang="en">Type: O. runTime: 30 min. Flags: Live, CC, HD 720p, HDTV, Subject to blackout. Subject to blackout.</desc>
    <premiere/>
    <subtitles type="teletext"/>
  </programme>
  <programme start="20250923023000Z" stop="20250923090000Z" channel="66112">
    <title lang="en">MLB Extra Innings</title>
    <category lang="en">Sports Filler</category>
    <desc lang="en">Type: O. runTime: 390 min. Duration: 240 min (differs from runTime). Flags: HD 720p, HDTV.</desc>
  </programme>
  <programme start="20250923090000Z" stop="20250923100000Z" channel="66112">
    <title lang="en">MLB Extra Innings</title>
    <category lang="en">Sports Filler</category>
    <desc lang="en">Type: O. runTime: 60 min. Flags: HD 720p, HDTV.</desc>
  </programme>
  <programme start="20250923100000Z" stop="20250923180000Z" channel="66112">
    <title lang="en">MLB Extra Innings</title>
    <category lang="en">Sports Filler</category>
    <desc lang="en">Type: O. runTime: 480 min. Flags: HD 720p, HDTV.</desc>
  </programme>
  <programme start="20250923180000Z" stop="20250923220000Z" channel="66112">
    <title lang="en">MLB Extra Innings</title>
    <category lang="en">Sports Filler</category>
    <desc lang="en">Type: O. runTime: 240 min. Flags: HD 720p, HDTV.</desc>
  </programme>
  <programme start="20250923220000Z" stop="20250923223000Z" channel="66112">
    <title lang="en">MLB Pregame</title>
    <category lang="en">Sports Filler</category>
    <desc lang="en">Type: O. runTime: 30 min. Flags: Live, CC, HD 720p, HDTV, Subject to blackout. Subject to blackout.</desc>
    <premiere/>
    <subtitles type="teletext"/>
  </programme>
  <programme start="20250923223000Z" stop="20250924013000Z" channel="66112">
    <title lang="en">MLB Baseball</title>
    <sub-title lang="en">Detroit Tigers at Cleveland Guardians</sub-title>
    <category lang="en">Sports</category>
    <desc lang="en">Type: S. runTime: 180 min. Flags: Live, CC, HD 720p, HDTV, Subject to blackout. Subject to blackout.</desc>
    <premiere/>
    <subtitles type="teletext"/>
  </programme>
  <programme start="20250924013000Z" stop="20250924020000Z" channel="66112">
    <title lang="en">MLB Extra Innings</title>
    <category lang="en">Sports Filler</category>
    <desc lang="en">Type: O. runTime: 30 min. Flags: HD 720p, HDTV.</desc>
  </programme>
  <programme start="20250924020000Z" stop="20250924050000Z" channel="66112">
    <title lang="en">MLB Baseball</title>
    <sub-title lang="en">Houston Astros at Athletics</sub-title>
    <category lang="en">Sports</category>
    <desc lang="en">Type: S. runTime: 180 min. Flags: Live, CC, HD 720p, HDTV, Subject to blackout. Subject to blackout.</desc>
    <premiere/>
    <subtitles type="teletext"/>
  </programme>
  <programme start="20250923050000Z" stop="20250923100000Z" channel="72810">
    <title lang="en">MLB Extra Innings</title>
    <category lang="en">Sports Filler</category>
    <desc lang="en">Type: O. runTime: 300 min. Flags: HD 720p, HDTV.</desc>
  </programme>
  <programme start="20250923100000Z" stop="20250923180000Z" channel="72810">
    <title lang="en">MLB Extra Innings</title>
    <category lang="en">Sports Filler</category>
    <desc lang="en">Type: O. runTime: 480 min. Flags: HD 720p, HDTV.</desc>
  </programme>
  <programme start="20250923180000Z" stop="20250923220000Z" channel="72810">
    <title lang="en">MLB Extra Innings</title>
    <category lang="en">Sports Filler</category>
    <desc lang="en">Type: O. runTime: 240 min. Flags: HD 720p, HDTV.</desc>
  </programme>
  <programme start="20250923220000Z" stop="20250923223000Z" channel="72810">
    <title lang="en">MLB Pregame</title>
    <category lang="en">Sports Filler</category>
    <desc lang="en">Type: O. runTime: 30 min. Flags: Live, CC, HD 720p, HDTV, Subject to blackout. Subject to blackout.</desc>
    <premiere/>
    <subtitles type="teletext"/>
  </programme>
  <programme start="20250923223000Z" stop="20250924013000Z" channel="72810">
    <title lang="en">MLB Baseball</title>
    <sub-title lang="en">Pittsburgh Pirates at Cincinnati Reds</sub-title>
    <category lang="en">Sports</category>
    <desc lang="en">Type: S. runTime: 180 min. Flags: Live, CC, HD 720p, HDTV, Subject to blackout. Subject to blackout.</desc>
    <premiere/>
    <subtitles type="teletext"/>
  </programme>
  <programme start="20250924013000Z" stop="20250924020000Z" channel="72810">
    <title lang="en">MLB Postgame</title>
    <category lang="en">Sports Filler</category>
    <desc lang="en">Type: O. runTime: 30 min. Flags: Live, CC, HD 720p, HDTV, Subject to blackout. Subject to blackout.</desc>
    <premiere/>
    <subtitles type="teletext"/>
  </programme>
  <programme start="20250924020000Z" stop="20250924083000Z" channel="72810">
    <title lang="en">MLB Extra Innings</title>
    <category lang="en">Sports Filler</category>
    <desc lang="en">Type: O. runTime: 390 min. Duration: 180 min (differs from runTime). Flags: HD 720p, HDTV.</desc>
  </programme>
  <programme start="20250923050000Z" stop="20250923100000Z" channel="72824">
    <title lang="en">MLB Extra Innings</title>
    <category lang="en">Sports Filler</category>
    <desc lang="en">Type: O. runTime: 300 min. Flags: HD 720p, HDTV.</desc>
  </programme>
  <programme start="20250923100000Z" stop="20250923180000Z" channel="72824">
    <title lang="en">MLB Extra Innings</title>
    <category lang="en">Sports Filler</category>
    <desc lang="en">Type: O. runTime: 480 min. Flags: HD 720p, HDTV.</desc>
  </programme>
  <programme start="20250923180000Z" stop="20250923220000Z" channel="72824">
    <title lang="en">MLB Extra Innings</title>
    <category lang="en">Sports Filler</category>
    <desc lang="en">Type: O. runTime: 240 min. Flags: HD 720p, HDTV.</desc>
  </programme>
  <programme start="20250923220000Z" stop="20250923223000Z" channel="72824">
    <title lang="en">MLB Pregame</title>
    <category lang="en">Sports Filler</category>
    <desc lang="en">Type: O. runTime: 30 min. Flags: Live, CC, HD 720p, HDTV, Subject to blackout. Subject to blackout.</desc>
    <premiere/>
    <subtitles type="teletext"/>
  </programme>
  <programme start="20250923223000Z" stop="20250924013000Z" channel="72824">
    <title lang="en">MLB Baseball</title>
    <sub-title lang="en">Miami Marlins at Philadelphia Phillies</sub-title>
    <category lang="en">Sports</category>
    <desc lang="en">Type: S. runTime: 180 min. Flags: Live, CC, HD 720p, HDTV, Subject to blackout. Subject to blackout.</desc>
    <premiere/>
    <subtitles type="teletext"/>
  </programme>
  <programme start="20250924013000Z" stop="20250924020000Z" channel="72824">
    <title lang="en">MLB Postgame</title>
    <category lang="en">Sports Filler</category>
    <desc lang="en">Type: O. runTime: 30 min. Flags: Live, CC, HD 720p, HDTV, Subject to blackout. Subject to blackout.</desc>
    <premiere/>
    <subtitles type="teletext"/>
  </programme>
  <programme start="20250924020000Z" stop="20250924083000Z" channel="72824">
    <title lang="en">MLB Extra Innings</title>
    <category lang="en">Sports Filler</category>
    <desc lang="en">Type: O. runTime: 390 min. Duration: 180 min (differs from runTime). Flags: HD 720p, HDTV.</desc>
  </programme>
  <programme start="20250923050000Z" stop="20250923100000Z" channel="72825">
    <title lang="en">MLB Extra Innings</title>
    <category lang="en">Sports Filler</category>
    <desc lang="en">Type: O. runTime: 300 min. Flags: HD 720p, HDTV.</desc>
  </programme>
  <programme start="20250923100000Z" stop="20250923180000Z" channel="72825">
    <title lang="en">MLB Extra Innings</title>
    <category lang="en">Sports Filler</category>
    <desc lang="en">Type: O. runTime: 480 min. Flags: HD 720p, HDTV.</desc>
  </programme>
  <programme start="20250923180000Z" stop="20250923230000Z" channel="72825">
    <title lang="en">MLB Extra Innings</title>
    <category lang="en">Sports Filler</category>
    <desc lang="en">Type: O. runTime: 300 min. Flags: HD 720p, HDTV.</desc>
  </programme>
  <programme start="20250923230000Z" stop="20250924020000Z" channel="72825">
    <title lang="en">MLB Baseball</title>
    <sub-title lang="en">Chicago White Sox at New York Yankees</sub-title>
    <category lang="en">Sports</category>
    <desc lang="en">Type: S. runTime: 180 min. Flags: Live, CC, HD 720p, HDTV, Subject to blackout. Subject to blackout.</desc>
    <premiere/>
    <subtitles type="teletext"/>
  </programme>
  <programme start="20250924020000Z" stop="20250924100000Z" channel="72825">
    <title lang="en">MLB Extra Innings</title>
    <category lang="en">Sports Filler</category>
    <desc lang="en">Type: O. runTime: 480 min. Duration: 180 min (differs from runTime). Flags: HD 720p, HDTV.</desc>
  </programme>
  <programme start="20250923050000Z" stop="20250923100000Z" channel="72826">
    <title lang="en">MLB Extra Innings</title>
    <category lang="en">Sports Filler</category>
    <desc lang="en">Type: O. runTime: 300 min. Flags: HD 720p, HDTV.</desc>
  </programme>
  <programme start="20250923100000Z" stop="20250923180000Z" channel="72826">
    <title lang="en">MLB Extra Innings</title>
    <category lang="en">Sports Filler</category>
    <desc lang="en">Type: O. runTime: 480 min. Flags: HD 720p, HDTV.</desc>
  </programme>
  <programme start="20250923180000Z" stop="20250923223000Z" channel="72826">
    <title lang="en">MLB Extra Innings</title>
    <category lang="en">Sports Filler</category>
    <desc lang="en">Type: O. runTime: 270 min. Flags: HD 720p, HDTV.</desc>
  </programme>
  <programme start="20250923223000Z" stop="20250923230000Z" channel="72826">
    <title lang="en">MLB Pregame</title>
    <category lang="en">Sports Filler</category>
    <desc lang="en">Type: O. runTime: 30 min. Flags: Live, CC, HD 720p, HDTV, Subject to blackout. Subject to blackout.</desc>
    <premiere/>
    <subtitles type="teletext"/>
  </programme>
  <programme start="20250923230000Z" stop="20250924020000Z" channel="72826">
    <title lang="en">MLB Baseball</title>
    <sub-title lang="en">Boston Red Sox at Toronto Blue Jays</sub-title>
    <category lang="en">Sports</category>
    <desc lang="en">Type: S. runTime: 180 min. Flags: Live, CC, HD 720p, HDTV, Subject to blackout. Subject to blackout.</desc>
    <premiere/>
    <subtitles type="teletext"/>
  </programme>
  <programme start="20250924020000Z" stop="20250924023000Z" channel="72826">
    <title lang="en">MLB Postgame</title>
    <category lang="en">Sports Filler</category>
    <desc lang="en">Type: O. runTime: 30 min. Flags: Live, CC, HD 720p, HDTV, Subject to blackout. Subject to blackout.</desc>
    <premiere/>
    <subtitles type="teletext"/>
  </programme>
  <programme start="20250924023000Z" stop="20250924090000Z" channel="72826">
    <title lang="en">MLB Extra Innings</title>
    <category lang="en">Sports Filler</category>
    <desc lang="en">Type: O. runTime: 390 min. Duration: 150 min (differs from runTime). Flags: HD 720p, HDTV.</desc>
  </programme>
  <programme start="20250923020000Z" stop="20250923100000Z" channel="72827">
    <title lang="en">MLB Extra Innings</title>
    <category lang="en">Sports Filler</category>
    <desc lang="en">Type: O. runTime: 480 min. Duration: 300 min (differs from runTime). Flags: HD 720p, HDTV.</desc>
  </programme>
  <programme start="20250923100000Z" stop="20250923180000Z" channel="72827">
    <title lang="en">MLB Extra Innings</title>
    <category lang="en">Sports Filler</category>
    <desc lang="en">Type: O. runTime: 480 min. Flags: HD 720p, HDTV.</desc>
  </programme>
  <programme start="20250923180000Z" stop="20250923230000Z" channel="72827">
    <title lang="en">MLB Extra Innings</title>
    <category lang="en">Sports Filler</category>
    <desc lang="en">Type: O. runTime: 300 min. Flags: HD 720p, HDTV.</desc>
  </programme>
  <programme start="20250923230000Z" stop="20250924020000Z" channel="72827">
    <title lang="en">MLB Baseball</title>
    <sub-title lang="en">Washington Nationals at Atlanta Braves</sub-title>
    <category lang="en">Sports</category>
    <desc lang="en">Type: S. runTime: 180 min. Flags: Live, CC, HD 720p, HDTV, Subject to blackout. Subject to blackout.</desc>
    <premiere/>
    <subtitles type="teletext"/>
  </programme>
  <programme start="20250924020000Z" stop="20250924023000Z" channel="72827">
    <title lang="en">MLB Postgame</title>
    <category lang="en">Sports Filler</category>
    <desc lang="en">Type: O. runTime: 30 min. Flags: Live, CC, HD 720p, HDTV, Subject to blackout. Subject to blackout.</desc>
    <premiere/>
    <subtitles type="teletext"/>
  </programme>
  <programme start="20250924023000Z" stop="20250924090000Z" channel="72827">
    <title lang="en">MLB Extra Innings</title>
    <category lang="en">Sports Filler</category>
    <desc lang="en">Type: O. runTime: 390 min. Duration: 150 min (differs from runTime). Flags: HD 720p, HDTV.</desc>
  </programme>
  <programme start="20250923020000Z" stop="20250923100000Z" channel="72828">
    <title lang="en">MLB Extra Innings</title>
    <category lang="en">Sports Filler</category>
    <desc lang="en">Type: O. runTime: 480 min. Duration: 300 min (differs from runTime). Flags: HD 720p, HDTV.</desc>
  </programme>
  <programme start="20250923100000Z" stop="20250923180000Z" channel="72828">
    <title lang="en">MLB Extra Innings</title>
    <category lang="en">Sports Filler</category>
    <desc lang="en">Type: O. runTime: 480 min. Flags: HD 720p, HDTV.</desc>
  </programme>
  <programme start="20250923180000Z" stop="20250923233000Z" channel="72828">
    <title lang="en">MLB Extra Innings</title>
    <category lang="en">Sports Filler</category>
    <desc lang="en">Type: O. runTime: 330 min. Flags: HD 720p, HDTV.</desc>
  </programme>
  <programme start="20250923233000Z" stop="20250924023000Z" channel="72828">
    <title lang="en">MLB Baseball</title>
    <sub-title lang="en">New York Mets at Chicago Cubs</sub-title>
    <category lang="en">Sports</category>
    <desc lang="en">Type: S. runTime: 180 min. Flags: Live, CC, HD 720p, HDTV, Subject to blackout. Subject to blackout.</desc>
    <premiere/>
    <subtitles type="teletext"/>
  </programme>
  <programme start="20250924023000Z" stop="20250924033000Z" channel="72828">
    <title lang="en">MLB Postgame</title>
    <category lang="en">Sports Filler</category>
    <desc lang="en">Type: O. runTime: 60 min. Flags: Live, CC, HD 720p, HDTV, Subject to blackout. Subject to blackout.</desc>
    <premiere/>
    <subtitles type="teletext"/>
  </programme>
  <programme start="20250924033000Z" stop="20250924090000Z" channel="72828">
    <title lang="en">MLB Extra Innings</title>
    <category lang="en">Sports Filler</category>
    <desc lang="en">Type: O. runTime: 330 min. Duration: 90 min (differs from runTime). Flags: HD 720p, HDTV.</desc>
  </programme>
</tv>
